hashstorm/__init__.py
hashstorm/__main__.py
hashstorm/banner.py
hashstorm/cli.py
hashstorm/config.py
hashstorm/core.py
hashstorm/wordlist/storm-wordlist.txt
hashstorm-0.2.0.dist-info/LICENSE
hashstorm-0.2.0.dist-info/METADATA
hashstorm-0.2.0.dist-info/WHEEL
hashstorm-0.2.0.dist-info/entry_points.txt
hashstorm-0.2.0.dist-info/RECORD
