Metadata-Version: 2.1
Name: hashstorm
Version: 0.2.0
Summary: Simples decrypter para hashes
Author: Guto Brutus
Author-email: guto@devops.pro.br
Requires-Python: >=3.10,<4.0
Classifier: Programming Language :: Python :: 3
Classifier: Programming Language :: Python :: 3.10
Classifier: Programming Language :: Python :: 3.11
Classifier: Programming Language :: Python :: 3.12
Requires-Dist: pyfiglet (>=1.0.2,<2.0.0)
Requires-Dist: typer[all] (>=0.9.0,<0.10.0)
